{"cameraMode":{"drawMode":0,"name":"Shaded","section":"Shading Mode"},"sceneLighting":true,"audioPlay":false,"sceneViewState":{"showFog":true,"showMaterialUpdate":false,"showSkybox":true,"showFlares":true,"showImageEffects":true,"showParticleSystems":true},"in2DMode":false,"pivot":{"x":-5.450469493865967,"y":-0.3770020008087158,"z":8.134822845458985},"rotation":{"x":0.12391010671854019,"y":-0.6018247008323669,"z":0.09520254284143448,"w":0.7831920385360718},"size":6.3868184089660648,"orthographic":false}